[
  {
    "NationalId": "30212101600183",
    "Name": "ألاء فتحي يوسف",
    "Level": "الاول",
    "FaceId": "",
    "MacId": ""
  },
  {
    "NationalId": "3397123003901",
    "Name": "احمد عبدالحميد",
    "Level": "الاول",
    "FaceId": "",
    "MacId": ""
  },
  {
    "NationalId": "30204041603888",
    "Name": "محمود ايمن",
    "Level": "الاول",
    "FaceId": "",
    "MacId": ""
  },
  {
    "Name": "ابراهيم عبد العاطى ابراهيم مختار",
    "NationalId": "221003",
    "Level": "الاول",
    "FaceId": "",
    "MacId": ""
  },
  {
    "Name": "احمد اسماعيل ياسين محمد التليسى",
    "NationalId": "231221",
    "Level": "الاول",
    "FaceId": "",
    "MacId": ""
  },
  {
    "Name": "احمد سراج سراج الدين على على",
    "NationalId": "231294",
    "Level": "الاول",
    "FaceId": "",
    "MacId": ""
  },
  {
    "Name": "احمد صبرى عبد السلام الصاوى القلاوى",
    "NationalId": "231173",
    "Level": "الاول",
    "FaceId": "",
    "MacId": ""
  },
  {
    "Name": "احمد عبد القادر محمود عبد القادر محمد",
    "NationalId": "231314",
    "Level": "الاول",
    "FaceId": "",
    "MacId": ""
  },
  {
    "Name": "احمد علاء محمود نفد",
    "NationalId": "231216",
    "Level": "الاول",
    "FaceId": "",
    "MacId": ""
  },
  {
    "Name": "احمد عماد احمد التهامى السيد الدهشان",
    "NationalId": "231032",
    "Level": "الاول",
    "FaceId": "",
    "MacId": ""
  },
  {
    "Name": "احمد محمد رضوان هلال رضوان",
    "NationalId": "231021",
    "Level": "الاول",
    "FaceId": "",
    "MacId": ""
  },
  {
    "Name": "احمد محمد على عبده الغريب",
    "NationalId": "231028",
    "Level": "الاول",
    "FaceId": "",
    "MacId": ""
  },
  {
    "Name": "احمد محمد مصطفى شريف",
    "NationalId": "231016",
    "Level": "الاول",
    "FaceId": "",
    "MacId": ""
  },
  {
    "Name": "احمد محمد هلال محمد هلال عطيه",
    "NationalId": "231036",
    "Level": "الاول",
    "FaceId": "",
    "MacId": ""
  },
  {
    "Name": "احمد نجيب فوزى نجيب",
    "NationalId": "231336",
    "Level": "الاول",
    "FaceId": "",
    "MacId": ""
  },
  {
    "Name": "احمد يوسف عبد العال احمد",
    "NationalId": "231281",
    "Level": "الاول",
    "FaceId": "",
    "MacId": ""
  },
  {
    "Name": "احمد يوسف فتحى عبد العليم سرحان",
    "NationalId": "221040",
    "Level": "الاول",
    "FaceId": "",
    "MacId": ""
  },
  {
    "Name": "ادهم محمد سمير المتولى خضر",
    "NationalId": "231005",
    "Level": "الاول",
    "FaceId": "",
    "MacId": ""
  },
  {
    "Name": "السيد اسماعيل عبد السميع اسماعيل صالح",
    "NationalId": "231263",
    "Level": "الاول",
    "FaceId": "",
    "MacId": ""
  },
  {
    "Name": "امجد هشام عبد السلام اسماعيل الجندى",
    "NationalId": "231234",
    "Level": "الاول",
    "FaceId": "",
    "MacId": ""
  },
  {
    "Name": "امين محمد محمد المتولى محمد المهدى",
    "NationalId": "231243",
    "Level": "الاول",
    "FaceId": "",
    "MacId": ""
  },
  {
    "Name": "ايمن اسامه محمد محمد رمضان شلبى",
    "NationalId": "231369",
    "Level": "الاول",
    "FaceId": "",
    "MacId": ""
  },
  {
    "Name": "بيشوى صموائيل عوض قسطنطين عوض",
    "NationalId": "231275",
    "Level": "الاول",
    "FaceId": "",
    "MacId": ""
  },
  {
    "Name": "تسنيم فريد محمد سعد محمد",
    "NationalId": "231006",
    "Level": "الاول",
    "FaceId": "",
    "MacId": ""
  },
  {
    "Name": "تقى صبرى فارس محمد المنسى",
    "NationalId": "231297",
    "Level": "الاول",
    "FaceId": "",
    "MacId": ""
  },
  {
    "Name": "حسام عادل الرفاعى طايل",
    "NationalId": "231099",
    "Level": "الاول",
    "FaceId": "",
    "MacId": ""
  },
  {
    "Name": "خلود السيد يوسف السعيد",
    "NationalId": "231328",
    "Level": "الاول",
    "FaceId": "",
    "MacId": ""
  },
  {
    "Name": "رفعت محمد عبد الغنى عبد الغنى البربرى البربرى",
    "NationalId": "231373",
    "Level": "الاول",
    "FaceId": "",
    "MacId": ""
  },
  {
    "Name": "زياد اشرف السيد لبيب السباعى",
    "NationalId": "231198",
    "Level": "الاول",
    "FaceId": "",
    "MacId": ""
  },
  {
    "Name": "سامح جمال السيد الحلاب",
    "NationalId": "231061",
    "Level": "الاول",
    "FaceId": "",
    "MacId": ""
  },
  {
    "Name": "سامح محمد ابراهيم منصور محمد",
    "NationalId": "231107",
    "Level": "الاول",
    "FaceId": "",
    "MacId": ""
  },
  {
    "Name": "سلمى محمود محمد السيد حسن",
    "NationalId": "221110",
    "Level": "الاول",
    "FaceId": "",
    "MacId": ""
  },
  {
    "Name": "سيف الدين اسامه محمد سيف الدين عبد اللطيف ابو العزم",
    "NationalId": "231346",
    "Level": "الاول",
    "FaceId": "",
    "MacId": ""
  },
  {
    "Name": "سيف الدين وائل ابراهيم شفيق المنهراوى",
    "NationalId": "231073",
    "Level": "الاول",
    "FaceId": "",
    "MacId": ""
  },
  {
    "Name": "سيف مجدى عبد الجواد محمد الملاح",
    "NationalId": "231074",
    "Level": "الاول",
    "FaceId": "",
    "MacId": ""
  },
  {
    "Name": "شهد ابراهيم مصطفى باشا ابراهيم",
    "NationalId": "231076",
    "Level": "الاول",
    "FaceId": "",
    "MacId": ""
  },
  {
    "Name": "صلاح اسامه حسنين على عبد البارى",
    "NationalId": "231231",
    "Level": "الاول",
    "FaceId": "",
    "MacId": ""
  },
  {
    "Name": "طارق العربى فتحى عبد الخالق حسين",
    "NationalId": "231255",
    "Level": "الاول",
    "FaceId": "",
    "MacId": ""
  },
  {
    "Name": "عادل خالد عبد الحميد على محمدبدوى",
    "NationalId": "231338",
    "Level": "الاول",
    "FaceId": "",
    "MacId": ""
  },
  {
    "Name": "عبد الرحمن اكرم محمود على محمد عامر",
    "NationalId": "231280",
    "Level": "الاول",
    "FaceId": "",
    "MacId": ""
  },
  {
    "Name": "عبد الرحمن تامر ابو بكر على اسماعيل",
    "NationalId": "231226",
    "Level": "الاول",
    "FaceId": "",
    "MacId": ""
  },
  {
    "Name": "عبد الرحمن عادل السيد عنان حسن عبده",
    "NationalId": "231167",
    "Level": "الاول",
    "FaceId": "",
    "MacId": ""
  },
  {
    "Name": "عبد الرحمن محمد رزق قاسم",
    "NationalId": "231141",
    "Level": "الاول",
    "FaceId": "",
    "MacId": ""
  },
  {
    "Name": "عبد الله خالد اسماعيل خاطر بصله",
    "NationalId": "231370",
    "Level": "الاول",
    "FaceId": "",
    "MacId": ""
  },
  {
    "Name": "عبير حسام محمود حجازى شهاب الدين",
    "NationalId": "231244",
    "Level": "الاول",
    "FaceId": "",
    "MacId": ""
  },
  {
    "Name": "علاء خالد عبد السلام السيد السعدنى",
    "NationalId": "231034",
    "Level": "الاول",
    "FaceId": "",
    "MacId": ""
  },
  {
    "Name": "عمار محمد محمد حامد شوارب",
    "NationalId": "231001",
    "Level": "الاول",
    "FaceId": "",
    "MacId": ""
  },
  {
    "Name": "عمر حسن عبد العزيز عبد الخالق",
    "NationalId": "231193",
    "Level": "الاول",
    "FaceId": "",
    "MacId": ""
  },
  {
    "Name": "عمر طارق الحسينى العيسوى",
    "NationalId": "231334",
    "Level": "الاول",
    "FaceId": "",
    "MacId": ""
  },
  {
    "Name": "عوض ايمن عوض عبد الغفور حندق",
    "NationalId": "231026",
    "Level": "الاول",
    "FaceId": "",
    "MacId": ""
  },
  {
    "Name": "غاليه احمد السيد منصور محمد",
    "NationalId": "231318",
    "Level": "الاول",
    "FaceId": "",
    "MacId": ""
  },
  {
    "Name": "فارس محمد رشاد رشاد عبد الله",
    "NationalId": "231366",
    "Level": "الاول",
    "FaceId": "",
    "MacId": ""
  },
  {
    "Name": "كريم محمد احمد وفا سليمان الحريرى",
    "NationalId": "231368",
    "Level": "الاول",
    "FaceId": "",
    "MacId": ""
  },
  {
    "Name": "مؤمن محسن مسعد حندق",
    "NationalId": "231109",
    "Level": "الاول",
    "FaceId": "",
    "MacId": ""
  },
  {
    "Name": "ماهر ياسر محمد عبد الحميد",
    "NationalId": "231241",
    "Level": "الاول",
    "FaceId": "",
    "MacId": ""
  },
  {
    "Name": "مايكل طلعت ذكرى بخيت",
    "NationalId": "231268",
    "Level": "الاول",
    "FaceId": "",
    "MacId": ""
  },
  {
    "Name": "مجدى محمود عبد الحق احمد ستو",
    "NationalId": "231146",
    "Level": "الاول",
    "FaceId": "",
    "MacId": ""
  },
  {
    "Name": "محمد ابراهيم مصطفى ابو الغيط",
    "NationalId": "231150",
    "Level": "الاول",
    "FaceId": "",
    "MacId": ""
  },
  {
    "Name": "محمد ابو المعاطى سعد ابو المعاطى محمد",
    "NationalId": "231003",
    "Level": "الاول",
    "FaceId": "",
    "MacId": ""
  },
  {
    "Name": "محمد السيد محمد ابراهيم الدسوقى",
    "NationalId": "231357",
    "Level": "الاول",
    "FaceId": "",
    "MacId": ""
  },
  {
    "Name": "محمد حسام ابراهيم محمد",
    "NationalId": "231343",
    "Level": "الاول",
    "FaceId": "",
    "MacId": ""
  },
  {
    "Name": "محمد شوقى عبد المنعم محمد حميده",
    "NationalId": "231115",
    "Level": "الاول",
    "FaceId": "",
    "MacId": ""
  },
  {
    "Name": "محمد علاء رمضان المصلحى سلام",
    "NationalId": "231199",
    "Level": "الاول",
    "FaceId": "",
    "MacId": ""
  },
  {
    "Name": "محمد هانى مسعد عبد الصمد البنا",
    "NationalId": "231230",
    "Level": "الاول",
    "FaceId": "",
    "MacId": ""
  },
  {
    "Name": "محمد ياسر عبده عبد الفتاح",
    "NationalId": "231290",
    "Level": "الاول",
    "FaceId": "",
    "MacId": ""
  },
  {
    "Name": "محمود السيد محمد احمد ابو العمايم",
    "NationalId": "231335",
    "Level": "الاول",
    "FaceId": "",
    "MacId": ""
  },
  {
    "Name": "محمود السيد محمد سليمان",
    "NationalId": "231098",
    "Level": "الاول",
    "FaceId": "",
    "MacId": ""
  },
  {
    "Name": "محمود عطيه احمد عبد العزيز عبد الله",
    "NationalId": "231131",
    "Level": "الاول",
    "FaceId": "",
    "MacId": ""
  },
  {
    "Name": "محمود كمال ابو واصل عوض احمد واصل",
    "NationalId": "231136",
    "Level": "الاول",
    "FaceId": "",
    "MacId": ""
  },
  {
    "Name": "محمود محمد عبد الفتاح احمد بدر",
    "NationalId": "231039",
    "Level": "الاول",
    "FaceId": "",
    "MacId": ""
  },
  {
    "Name": "محمود وائل عبد السلام البدراوى عاشور",
    "NationalId": "231327",
    "Level": "الاول",
    "FaceId": "",
    "MacId": ""
  },
  {
    "Name": "محمود يوسف حمدى محمود عبد الفتاح",
    "NationalId": "231168",
    "Level": "الاول",
    "FaceId": "",
    "MacId": ""
  },
  {
    "Name": "مريم نادر عبد الله ابراهيم ابراهيم",
    "NationalId": "231101",
    "Level": "الاول",
    "FaceId": "",
    "MacId": ""
  },
  {
    "Name": "مصطفى ابراهيم مصطفى احمد",
    "NationalId": "231070",
    "Level": "الاول",
    "FaceId": "",
    "MacId": ""
  },
  {
    "Name": "مصطفى احمد انور الحنفى صلاح",
    "NationalId": "231185",
    "Level": "الاول",
    "FaceId": "",
    "MacId": ""
  },
  {
    "Name": "مصطفى احمد رمضان عبد الحميد الحايس",
    "NationalId": "231224",
    "Level": "الاول",
    "FaceId": "",
    "MacId": ""
  },
  {
    "Name": "مصطفى محمد الشحات السعيد سالم",
    "NationalId": "231253",
    "Level": "الاول",
    "FaceId": "",
    "MacId": ""
  },
  {
    "Name": "ندى ابو بكر محمود ابو بكر عيسوى",
    "NationalId": "231066",
    "Level": "الاول",
    "FaceId": "",
    "MacId": ""
  },
  {
    "Name": "ندى عبد الفتاح منصور اسماعيل",
    "NationalId": "231157",
    "Level": "الاول",
    "FaceId": "",
    "MacId": ""
  },
  {
    "Name": "نور محمد صلاح محمد عوض",
    "NationalId": "231180",
    "Level": "الاول",
    "FaceId": "",
    "MacId": ""
  },
  {
    "Name": "هويدا محمود احمد فرحات يوسف العيسوى",
    "NationalId": "231049",
    "Level": "الاول",
    "FaceId": "",
    "MacId": ""
  },
  {
    "Name": "ياسين صبح محمد السيد",
    "NationalId": "231284",
    "Level": "الاول",
    "FaceId": "",
    "MacId": ""
  }

]